{
  "$schema": "https://json-schema.org/draft/2020-12/schema",
  "$id": "https://raw.githubusercontent.com/api-evangelist/amazon-storage-gateway/refs/heads/main/json-schema/amazon-storage-gateway-active-directory-status-schema.json",
  "title": "ActiveDirectoryStatus",
  "description": "ActiveDirectoryStatus schema from Amazon Storage Gateway API",
  "type": "string",
  "enum": [
    "ACCESS_DENIED",
    "DETACHED",
    "JOINED",
    "JOINING",
    "NETWORK_ERROR",
    "TIMEOUT",
    "UNKNOWN_ERROR"
  ]
}